Workbook

Sheet Read me
A1: Reconciliation rulebook
A2: Fee values are from the issuer MITC stated correct as on 25 September 2026.
A4: Item | B4: Details
A5: Purpose | B5: The rulebook for the reconciliation engine. Each rule says what a correct statement looks like and when to raise an alert.
A6: For the dummy statements | B6: Each dummy statement should break one rule. The "How to break it" column on the rule sheets says how. Record which Rule ID each statement breaks so the alerts can be scored.
A7: Sheets | B7: Bank fee rules: rules taken from the issuer MITC. Common-sense rules: rules from the project scope. Not errors: cases that look wrong but are allowed, for testing false alarms. Parameters and Late fee slabs: the numbers the engine reads. Source: where the numbers came from.
A8: Assumption 1 | B8: The dummy card is a standard unsecured card: finance charge 3.75% per month and foreign currency fee 3.5%. Premium, secured and defence variants have different rates in the MITC and are left out.
A9: Assumption 2 | B9: GST is 18% on every fee, interest and charge. The split into central and state tax depends on the cardholder state; the total is the same.
A10: Assumption 3 | B10: Annual fee, credit limit, and each EMI plan (amount, rate, tenure, processing fee) are not fixed by the MITC. Set them per dummy card and write them on the statement.
A11: Assumption 4 | B11: Allow a rounding tolerance of Rs. 1 when comparing expected and actual amounts.
A12: Naming | B12: The rule sheets say "issuer" and do not name the bank. Only the Source sheet names the document; remove that sheet before sharing outside the team.
A13: Colour | B13: Blue numbers on the Parameters and Late fee slabs sheets are inputs copied from the MITC. Change them there if the policy changes.

Sheet Bank fee rules
A1: Bank fee rules
A2: From the issuer MITC. All fees are before GST; GST is checked separately by rule F13.
A4: Rule ID | B4: Rule | C4: When it applies | D4: Expected value or formula | E4: Flag (raise alert) if | F4: How to break it in a dummy statement | G4: Worked example | H4: MITC section
A5: F01 | B5: Finance charge (interest) rate | C5: Total amount due of the previous statement was not paid in full by the due date | D5: Balance x 45% x days / 365 (3.75% per month), counted from the transaction date | E5: Interest charged differs from the formula | F5: Charge interest at a higher rate, e.g. 4.5% per month | G5: Rs. 6,000 for 38 days: 45% x 38/365 x 6,000 = Rs. 281.10 (MITC example) | H5: 1F
A6: F02 | B6: No interest after full payment | C6: Previous total amount due was paid in full by the due date, no balance carried forward, no cash advance | D6: Finance charge = 0 | E6: Any finance charge appears | F6: Show full payment on time, then add a finance charge line | H6: 1E, 1F
A7: F03 | B7: Minimum finance charge | C7: A finance charge applies but the computed amount is small | D7: Finance charge is at least Rs. 25 (before tax) | E7: Finance charge is above 0 and below Rs. 25 | F7: Charge Rs. 10 interest on a small unpaid balance | H7: 1F, 8
A8: F04 | B8: Interest on cash advance | C8: Cash withdrawn using the card | D8: Interest from the withdrawal date until paid; no interest-free period | E8: Interest is counted from a date other than the withdrawal date | F8: Count interest from the statement start instead of the withdrawal date | H8: 1B, 1F, 8
A9: F05 | B9: Cash advance fee | C9: Each cash withdrawal at an ATM | D9: Higher of 2.5% of the amount or Rs. 500 | E9: Fee differs from the formula, or is charged twice for one withdrawal | F9: Charge 3.5%, or charge Rs. 300 on a small withdrawal | G9: Rs. 10,000: 2.5% = 250, so fee = Rs. 500. Rs. 30,000: fee = Rs. 750 | H9: 1B, 8
A10: F06 | B10: Late payment fee | C10: Minimum amount due not paid by the due date plus 3 grace days | D10: Fixed slab by outstanding amount due (see Late fee slabs sheet) | E10: Fee charged although the minimum due was paid on time, or the wrong slab is used | F10: Use the next higher slab, or charge the fee when payment was on time | G10: Amount due Rs. 10,500 falls in the 10,000 to 25,000 slab: fee = Rs. 950 (MITC example) | H10: 1H, 8
A11: F07 | B11: Additional late payment charge | C11: Minimum amount due missed for two consecutive cycles | D11: Rs. 100 extra per cycle until the minimum due is cleared | E11: Charged when fewer than two consecutive cycles were missed, or the amount is not Rs. 100 | F11: Add the Rs. 100 charge after only one missed cycle | H11: 1H, 8
A12: F08 | B12: Over-limit fee | C12: Outstanding amount exceeds the credit limit | D12: Higher of 2.5% of the amount over the limit or Rs. 600; once per billing cycle | E12: Charged while within the limit, wrong amount, or more than once in a cycle | F12: Charge it twice in one cycle, or when the balance is under the limit | G12: Limit Rs. 1,00,000, outstanding Rs. 1,30,000: 2.5% x 30,000 = Rs. 750 | H12: 1I, 8
A13: F09 | B13: Payment dishonour fee | C13: A payment bounces | D13: Higher of 2% of the payment amount or Rs. 500 | E13: Fee differs, or is charged with no bounced payment on the statement | F13: Charge the fee with no dishonoured payment listed | G13: Payment Rs. 20,000: 2% = 400, so fee = Rs. 500 | H13: 1J, 8
A14: F10 | B14: Foreign currency transaction fee | C14: Transaction in a foreign currency | D14: 3.5% of the INR-converted amount | E14: Fee differs from 3.5% of the converted amount | F14: Charge 5% on a foreign purchase | G14: Rs. 10,000 converted: fee = Rs. 350 | H14: 1N, 8
A15: F11 | B15: Dynamic currency conversion fee | C15: INR transaction of Rs. 1,000 or more at an international location or overseas-registered merchant | D15: 3.5% of the transaction amount | E15: Charged on a transaction below Rs. 1,000, on a domestic merchant, or at a different rate | F15: Charge it on an Rs. 800 transaction | H15: 1N, 8
A16: F12 | B16: Annual or renewal fee | C16: Once every 12 months | D16: The fee set for the dummy card (MITC range Rs. 0 to Rs. 9,999); waived if annual spend crossed the card's waiver threshold | E16: Charged more than once in 12 months, amount differs from the card's fee, or charged although the waiver threshold was met | F16: Charge the fee in two different months of the same year | H16: 1A, 8
A17: F13 | B17: GST on fees and interest | C17: Any fee, interest or charge on the statement | D17: 18% of the sum of fees, interest and charges | E17: GST differs from 18% of that sum, or GST is charged on purchases | F17: Show GST at 28%, or GST with no fee on the statement | G17: Annual fee Rs. 500: GST = Rs. 90 (MITC example) | H17: 8
A18: F14 | B18: Minimum amount due | C18: Every statement | D18: 100% of GST + 100% of EMI + 100% of fees + 100% of finance charges + over-limit amount + 2% of remaining balance (at least Rs. 200), plus any unpaid minimum due from earlier statements | E18: Printed minimum due differs from the formula | F18: Print a minimum due that leaves out the EMI or fees | G18: GST 90 + fee 500 + 2% x 6,000 = Rs. 710 (MITC example) | H18: 1G, 3b
A19: F15 | B19: Payment due date | C19: Every statement | D19: Statement date + 20 days (as used in the MITC examples) | E19: Due date is earlier than statement date + 20 days | F19: Print a due date 10 days after the statement date | G19: Statement 2 Feb: due 22 Feb (MITC example) | H19: 1F examples
A20: F16 | B20: Utility payment fee | C20: Utility payments in a billing cycle total more than Rs. 50,000 | D20: 1% of the total utility payments in that cycle | E20: Charged when the total is Rs. 50,000 or less, or the amount is wrong | F20: Charge 1% when utility payments total Rs. 30,000 | G20: Utility total Rs. 64,000: fee = Rs. 640 (MITC example) | H20: 1K, 8
A21: F17 | B21: Education payment fee | C21: Education payment made through a third-party app | D21: 1% of the transaction amount | E21: Fee differs from 1%, or is charged on a payment made directly to the school or college | F21: Charge 2% on an education payment | H21: 1L, 8
A22: F18 | B22: Wallet load fee | C22: Each wallet load above Rs. 1,000 | D22: 1% of the transaction amount | E22: Charged on a load of Rs. 1,000 or less, or the amount is wrong | F22: Charge the fee on an Rs. 500 wallet load | G22: Wallet load Rs. 5,000: fee = Rs. 50 | H22: 1M, 8
A23: F19 | B23: Rent payment processing fee | C23: Each rent payment transaction | D23: Rs. 199 per transaction | E23: Amount differs, or charged twice for one rent payment | F23: Charge Rs. 199 twice for a single rent payment | H23: 1N, 8
A24: F20 | B24: Fuel surcharge | C24: Purchase at a petrol pump | D24: 1% of the transaction amount, plus tax | E24: Surcharge is more than 1% | F24: Charge a 2.5% fuel surcharge | H24: 8
A25: F21 | B25: Cash payment fee | C25: Bill paid in cash at a bank branch | D25: Rs. 250 | E25: Amount differs, or charged when no cash payment was made | F25: Charge the fee on an online payment | H25: 1C, 8
A26: F22 | B26: Cheque payment fee | C26: Bill paid by cheque | D26: Rs. 200 | E26: Amount differs, or charged when no cheque payment was made | F26: Charge the fee on an online payment | H26: 1N, 8
A27: F23 | B27: Rewards redemption fee | C27: Reward points redeemed for physical products, statement credit or physical vouchers | D27: Rs. 99 | E27: Amount differs, or charged with no redemption | F27: Charge Rs. 199 for one redemption | H27: 1N, 8
A28: F24 | B28: Card replacement fee | C28: Card replaced | D28: Rs. 100 to Rs. 250 | E28: Amount is outside the range, or charged with no replacement | F28: Charge Rs. 500 for a replacement | H28: 1N, 8
A29: F25 | B29: Interest on unpaid EMI | C29: An EMI instalment is billed and not paid by the due date | D29: Unpaid instalment x 45% x days / 365 | E29: Interest on unpaid EMI differs from the formula, or is charged although the EMI was paid | F29: Charge EMI interest although the instalment was paid on time | G29: Rs. 6,730.03 unpaid for 11 days: Rs. 91.27 (MITC example) | H29: 1F example 5

Sheet Common-sense rules
A1: Common-sense rules
A2: These come from the project scope, not the issuer documents. EMI terms are set per dummy plan.
A4: Rule ID | B4: Rule | C4: What to check | D4: Flag (raise alert) if | E4: How to break it in a dummy statement
A5: C01 | B5: Duplicate transaction | C5: Same merchant, amount and date appear twice | D5: A second identical transaction is charged | E5: Repeat one purchase line with the same date and amount
A6: C02 | B6: EMI missing | C6: An ongoing EMI should appear every month until its last instalment | D6: An ongoing EMI is not on this month's statement | E6: Leave instalment 4 of 9 out of one month
A7: C03 | B7: EMI repeated | C7: Each EMI should appear once per month | D7: The same EMI is charged twice in one month | E7: Add the same EMI line twice
A8: C04 | B8: EMI amount changed | C8: EMI amount should match the plan and earlier months | D8: The amount differs from the plan amount | E8: Raise one month's EMI by a few hundred rupees
A9: C05 | B9: EMI instalment count | C9: Instalment number should go up by one each month and stop at the tenure | D9: A number is skipped or repeated, or an EMI is charged after the last instalment | E9: Charge a 10th instalment on a 9-month plan
A10: C06 | B10: EMI amount matches the plan | C10: EMI = P x r x (1+r)^n / ((1+r)^n - 1), where P is the amount, r the monthly rate, n the tenure | D10: EMI on the statement differs from the formula for the stated plan | E10: State an 18% plan but bill the EMI of a 24% plan. Check: Rs. 36,295 at 18% a year for 9 months gives Rs. 4,341.24 (MITC illustration)
A11: C07 | B11: Subscription price increase | C11: A recurring merchant should charge the same as last month | D11: This month's charge is higher than last month's | E11: Change a Rs. 799 subscription to Rs. 999
A12: C08 | B12: New recurring charge | C12: A merchant that starts charging every month | D12: A new subscription appears that was not in earlier months | E12: Add a new monthly merchant from one month onward
A13: C09 | B13: Missing refund | C13: A refund or reversal that the earlier statements lead us to expect | D13: The refund is not on the statement | E13: Show a cancelled order with no refund line the next month
A14: C10 | B14: Totals do not add up | C14: Opening balance + purchases + fees + interest + GST - payments - refunds | D14: The result does not equal the closing balance | E14: Print a closing balance that is Rs. 1,000 too high
A15: C11 | B15: Fee with no trigger | C15: Every fee should have a matching event on the statement | D15: A fee appears with nothing that triggers it | E15: Add a late fee, cash advance fee or forex fee with no matching event
A16: C12 | B16: Unknown or new merchant | C16: Merchants seen in earlier months | D16: A large charge from a merchant never seen before | E16: Add one high-value charge from a new merchant name

Sheet Not errors
A1: Not errors
A2: Use a few of these in the dummy statements to check that the tool does not raise false alarms.
A4: Case ID | B4: Looks wrong | C4: Why it is allowed (do not raise an alert) | D4: MITC section
A5: N01 | B5: Payment made up to 3 days after the due date, with no late fee | C5: A 3-day grace period applies when nothing is overdue from earlier cycles | D5: 8
A6: N02 | B6: A purchase is refunded but the foreign currency fee is not | C6: Foreign currency and currency conversion fees are not reversed on refunds | D6: 1N
A7: N03 | B7: A transaction is reversed but the over-limit fee stays | C7: The over-limit fee is not reversed on reversal, cancellation or refund | D7: 1I
A8: N04 | B8: A rent payment is refunded but the Rs. 199 fee stays | C8: The rent processing fee is not reversed | D8: 1N
A9: N05 | B9: No payment made, yet no late fee | C9: A refund credited before the due date for an earlier-cycle purchase counts as payment if it covers the minimum due | D9: 1H example 3, 3j
A10: N06 | B10: Interest charged in a month where the full bill was paid | C10: If an earlier balance was carried forward, interest runs on it until the payment date | D10: 1F example 4
A11: N07 | B11: Interest charged on new purchases straight away | C11: The interest-free period is suspended while any earlier balance is outstanding | D11: 1E

Sheet EMI plans
A1: EMI plan terms
A2: Team-chosen dummy plans, inside the issuer's published Flexipay terms. Blue cells are inputs; the rest are formulas. Print the plan terms on the dummy statement.
A4: Plan ID | B4: Booking amount (Rs.) | C4: Annual interest rate | D4: Tenure (months) | E4: Processing fee rate | F4: Monthly EMI (Rs.) | G4: Processing fee (Rs.) | H4: GST on processing fee (Rs.) | I4: Total interest (Rs.) | J4: Total of all EMIs (Rs.)
A5: EMI-A | B5: 30000 | C5: 0.12 | D5: 3 | E5: 0 | F5: =ROUND(PMT(C5/12,D5,-B5),2) -> 10200.66 | G5: =ROUND(B5*E5,2) -> 0 | H5: =ROUND(G5*Parameters!$B$19,2) -> 0 | I5: =F5*D5-B5 -> 601.98 | J5: =F5*D5 -> 30601.98
A6: EMI-B | B6: 36295 | C6: 0.18 | D6: 9 | E6: 0.01 | F6: =ROUND(PMT(C6/12,D6,-B6),2) -> 4341.24 | G6: =ROUND(B6*E6,2) -> 362.95 | H6: =ROUND(G6*Parameters!$B$19,2) -> 65.33 | I6: =F6*D6-B6 -> 2776.16 | J6: =F6*D6 -> 39071.16
A7: EMI-C | B7: 60000 | C7: 0.15 | D7: 12 | E7: 0.01 | F7: =ROUND(PMT(C7/12,D7,-B7),2) -> 5415.5 | G7: =ROUND(B7*E7,2) -> 600 | H7: =ROUND(G7*Parameters!$B$19,2) -> 108 | I7: =F7*D7-B7 -> 4986 | J7: =F7*D7 -> 64986
A10: Assumption: every instalment is the same amount. The issuer adjusts the first instalment's interest for the actual number of days; the dummy statements ignore this.
A11: Assumption: processing fee is 0% for a 3-month tenure and 1% of the booking amount for longer tenures, as in the issuer's Flexipay terms. Any minimum or maximum cap on the fee is not confirmed.
A12: Plan EMI-B matches the MITC illustration (Rs. 36,295 at 18% for 9 months gives an EMI of Rs. 4,341.24).
A13: The processing fee and its GST are billed once, in the month the plan is booked.

Sheet EMI schedule
A1: EMI schedule
A2: Month-by-month split for each plan, for rules C02 to C06. All cells are formulas driven by the EMI plans sheet.
A4: Plan ID | B4: Instalment no. | C4: Statement label | D4: Opening principal (Rs.) | E4: Interest part (Rs.) | F4: Principal part (Rs.) | G4: EMI (Rs.) | H4: Closing principal (Rs.)
A5: EMI-A | B5: 1 | C5: EMI 01/03 | D5: ='EMI plans'!$B$5 -> 30000 | E5: =ROUND(D5*'EMI plans'!$C$5/12,2) -> 300 | F5: =G5-E5 -> 9900.66 | G5: ='EMI plans'!$F$5 -> 10200.66 | H5: =D5-F5 -> 20099.34
A6: EMI-A | B6: 2 | C6: EMI 02/03 | D6: =H5 -> 20099.34 | E6: =ROUND(D6*'EMI plans'!$C$5/12,2) -> 200.99 | F6: =G6-E6 -> 9999.67 | G6: ='EMI plans'!$F$5 -> 10200.66 | H6: =D6-F6 -> 10099.67
A7: EMI-A | B7: 3 | C7: EMI 03/03 | D7: =H6 -> 10099.67 | E7: =ROUND(D7*'EMI plans'!$C$5/12,2) -> 101 | F7: =G7-E7 -> 10099.66 | G7: ='EMI plans'!$F$5 -> 10200.66 | H7: =D7-F7 -> 0.01
A8: EMI-B | B8: 1 | C8: EMI 01/09 | D8: ='EMI plans'!$B$6 -> 36295 | E8: =ROUND(D8*'EMI plans'!$C$6/12,2) -> 544.43 | F8: =G8-E8 -> 3796.81 | G8: ='EMI plans'!$F$6 -> 4341.24 | H8: =D8-F8 -> 32498.19
A9: EMI-B | B9: 2 | C9: EMI 02/09 | D9: =H8 -> 32498.19 | E9: =ROUND(D9*'EMI plans'!$C$6/12,2) -> 487.47 | F9: =G9-E9 -> 3853.77 | G9: ='EMI plans'!$F$6 -> 4341.24 | H9: =D9-F9 -> 28644.42
A10: EMI-B | B10: 3 | C10: EMI 03/09 | D10: =H9 -> 28644.42 | E10: =ROUND(D10*'EMI plans'!$C$6/12,2) -> 429.67 | F10: =G10-E10 -> 3911.57 | G10: ='EMI plans'!$F$6 -> 4341.24 | H10: =D10-F10 -> 24732.85
A11: EMI-B | B11: 4 | C11: EMI 04/09 | D11: =H10 -> 24732.85 | E11: =ROUND(D11*'EMI plans'!$C$6/12,2) -> 370.99 | F11: =G11-E11 -> 3970.25 | G11: ='EMI plans'!$F$6 -> 4341.24 | H11: =D11-F11 -> 20762.6
A12: EMI-B | B12: 5 | C12: EMI 05/09 | D12: =H11 -> 20762.6 | E12: =ROUND(D12*'EMI plans'!$C$6/12,2) -> 311.44 | F12: =G12-E12 -> 4029.8 | G12: ='EMI plans'!$F$6 -> 4341.24 | H12: =D12-F12 -> 16732.8
A13: EMI-B | B13: 6 | C13: EMI 06/09 | D13: =H12 -> 16732.8 | E13: =ROUND(D13*'EMI plans'!$C$6/12,2) -> 250.99 | F13: =G13-E13 -> 4090.25 | G13: ='EMI plans'!$F$6 -> 4341.24 | H13: =D13-F13 -> 12642.55
A14: EMI-B | B14: 7 | C14: EMI 07/09 | D14: =H13 -> 12642.55 | E14: =ROUND(D14*'EMI plans'!$C$6/12,2) -> 189.64 | F14: =G14-E14 -> 4151.6 | G14: ='EMI plans'!$F$6 -> 4341.24 | H14: =D14-F14 -> 8490.95
A15: EMI-B | B15: 8 | C15: EMI 08/09 | D15: =H14 -> 8490.95 | E15: =ROUND(D15*'EMI plans'!$C$6/12,2) -> 127.36 | F15: =G15-E15 -> 4213.88 | G15: ='EMI plans'!$F$6 -> 4341.24 | H15: =D15-F15 -> 4277.07
A16: EMI-B | B16: 9 | C16: EMI 09/09 | D16: =H15 -> 4277.07 | E16: =ROUND(D16*'EMI plans'!$C$6/12,2) -> 64.16 | F16: =G16-E16 -> 4277.08 | G16: ='EMI plans'!$F$6 -> 4341.24 | H16: =D16-F16 -> -0.01
A17: EMI-C | B17: 1 | C17: EMI 01/12 | D17: ='EMI plans'!$B$7 -> 60000 | E17: =ROUND(D17*'EMI plans'!$C$7/12,2) -> 750 | F17: =G17-E17 -> 4665.5 | G17: ='EMI plans'!$F$7 -> 5415.5 | H17: =D17-F17 -> 55334.5
A18: EMI-C | B18: 2 | C18: EMI 02/12 | D18: =H17 -> 55334.5 | E18: =ROUND(D18*'EMI plans'!$C$7/12,2) -> 691.68 | F18: =G18-E18 -> 4723.82 | G18: ='EMI plans'!$F$7 -> 5415.5 | H18: =D18-F18 -> 50610.68
A19: EMI-C | B19: 3 | C19: EMI 03/12 | D19: =H18 -> 50610.68 | E19: =ROUND(D19*'EMI plans'!$C$7/12,2) -> 632.63 | F19: =G19-E19 -> 4782.87 | G19: ='EMI plans'!$F$7 -> 5415.5 | H19: =D19-F19 -> 45827.81
A20: EMI-C | B20: 4 | C20: EMI 04/12 | D20: =H19 -> 45827.81 | E20: =ROUND(D20*'EMI plans'!$C$7/12,2) -> 572.85 | F20: =G20-E20 -> 4842.65 | G20: ='EMI plans'!$F$7 -> 5415.5 | H20: =D20-F20 -> 40985.16
A21: EMI-C | B21: 5 | C21: EMI 05/12 | D21: =H20 -> 40985.16 | E21: =ROUND(D21*'EMI plans'!$C$7/12,2) -> 512.31 | F21: =G21-E21 -> 4903.19 | G21: ='EMI plans'!$F$7 -> 5415.5 | H21: =D21-F21 -> 36081.97
A22: EMI-C | B22: 6 | C22: EMI 06/12 | D22: =H21 -> 36081.97 | E22: =ROUND(D22*'EMI plans'!$C$7/12,2) -> 451.02 | F22: =G22-E22 -> 4964.48 | G22: ='EMI plans'!$F$7 -> 5415.5 | H22: =D22-F22 -> 31117.49
A23: EMI-C | B23: 7 | C23: EMI 07/12 | D23: =H22 -> 31117.49 | E23: =ROUND(D23*'EMI plans'!$C$7/12,2) -> 388.97 | F23: =G23-E23 -> 5026.53 | G23: ='EMI plans'!$F$7 -> 5415.5 | H23: =D23-F23 -> 26090.96
A24: EMI-C | B24: 8 | C24: EMI 08/12 | D24: =H23 -> 26090.96 | E24: =ROUND(D24*'EMI plans'!$C$7/12,2) -> 326.14 | F24: =G24-E24 -> 5089.36 | G24: ='EMI plans'!$F$7 -> 5415.5 | H24: =D24-F24 -> 21001.6
A25: EMI-C | B25: 9 | C25: EMI 09/12 | D25: =H24 -> 21001.6 | E25: =ROUND(D25*'EMI plans'!$C$7/12,2) -> 262.52 | F25: =G25-E25 -> 5152.98 | G25: ='EMI plans'!$F$7 -> 5415.5 | H25: =D25-F25 -> 15848.62
A26: EMI-C | B26: 10 | C26: EMI 10/12 | D26: =H25 -> 15848.62 | E26: =ROUND(D26*'EMI plans'!$C$7/12,2) -> 198.11 | F26: =G26-E26 -> 5217.39 | G26: ='EMI plans'!$F$7 -> 5415.5 | H26: =D26-F26 -> 10631.23
A27: EMI-C | B27: 11 | C27: EMI 11/12 | D27: =H26 -> 10631.23 | E27: =ROUND(D27*'EMI plans'!$C$7/12,2) -> 132.89 | F27: =G27-E27 -> 5282.61 | G27: ='EMI plans'!$F$7 -> 5415.5 | H27: =D27-F27 -> 5348.62
A28: EMI-C | B28: 12 | C28: EMI 12/12 | D28: =H27 -> 5348.62 | E28: =ROUND(D28*'EMI plans'!$C$7/12,2) -> 66.86 | F28: =G28-E28 -> 5348.64 | G28: ='EMI plans'!$F$7 -> 5415.5 | H28: =D28-F28 -> -0.02

Sheet Parameters
A1: Parameters
A2: Blue values are inputs copied from the issuer MITC. Percentages are stored as fractions.
A4: Parameter | B4: Value | C4: Unit | D4: Used by | E4: MITC section
A5: finance_charge_monthly | B5: 0.0375 | C5: per month | D5: F01, F04, F25 | E5: 1F, 8
A6: finance_charge_annual | B6: 0.45 | C6: per year | D6: F01, F04, F25 | E6: 1F, 8
A7: min_finance_charge | B7: 25 | C7: Rs. | D7: F03 | E7: 1F, 8
A8: cash_advance_fee_rate | B8: 0.025 | C8: of amount | D8: F05 | E8: 1B, 8
A9: cash_advance_fee_min | B9: 500 | C9: Rs. | D9: F05 | E9: 1B, 8
A10: late_fee_grace_days | B10: 3 | C10: days | D10: F06 | E10: 8
A11: additional_late_charge | B11: 100 | C11: Rs. | D11: F07 | E11: 1H, 8
A12: overlimit_fee_rate | B12: 0.025 | C12: of over-limit amount | D12: F08 | E12: 1I, 8
A13: overlimit_fee_min | B13: 600 | C13: Rs. | D13: F08 | E13: 1I, 8
A14: dishonour_fee_rate | B14: 0.02 | C14: of payment amount | D14: F09 | E14: 1J, 8
A15: dishonour_fee_min | B15: 500 | C15: Rs. | D15: F09 | E15: 1J, 8
A16: forex_fee_rate | B16: 0.035 | C16: of INR amount | D16: F10 | E16: 1N, 8
... A37: rounding_tolerance | B37: 1 | C37: Rs. (team assumption, not from the MITC) | D37: All rules | E37: -

Sheet Late fee slabs
A1: Late fee slabs
A2: Rule F06. Pick the row where the outstanding amount due is greater than the lower bound and up to the upper bound. Fee is before GST.
A4: Amount due greater than (Rs.) | B4: Up to (Rs.) | C4: Late fee (Rs.)
A5: 0 | B5: 100 | C5: 0
A6: 100 | B6: 500 | C6: 100
A7: 500 | B7: 1000 | C7: 500
A8: 1000 | B8: 10000 | C8: 750
A9: 10000 | B9: 25000 | C9: 950
A10: 25000 | B10: 50000 | C10: 1100
A11: 50000 | B11: No upper limit | C11: 1300

Sheet Source
A1: Source
A2: Where the fee values on the other sheets came from.
A4: Item | B4: Details
A5: Document | B5: SBI Card, Most Important Terms and Conditions (English), version FY 27, 16
A6: Stated date | B6: All information correct as on 25 September 2026, per the document
A7: URL | B7: https://www.sbicard.com/sbi-card-en/assets/docs/pdf/most-important-terms-and-conditions/mitc-english.pdf
A8: Retrieved | B8: 6 October 2026
A9: Not in the MITC | B9: EMI processing fee and EMI interest rate per plan, and the annual fee of the specific dummy card. These are set by the team per dummy card.
A10: Note | B10: Internal reference only. Remove this sheet before sharing outside the team, since the project does not name the bank.
A11: EMI terms | B11: SBI Card Flexipay terms and conditions (sbicard.com, tnc documents). Rate range and processing fee vary by offer and customer segment; the EMI plans sheet uses fixed team-chosen values inside those terms.
